{
  " ( Repeating every week ) " : " (Repetir cada semana)   ",
  " @" : " @ ",
  " Add / Remove Day Off" : " Añadir/Eliminar día desactivado ",
  " Add / Remove Employee" : " Añadir/Eliminar empleado ",
  " are you sure you wish to continue?" : " ¿Está seguro de que desea continuar? ",
  " Availability" : " Disponibilidad ",
  " by " : " por   ",
  " Copy Shift " : " Copiar Mayús.   ",
  " Day Off" : " Día apagado ",
  " Default Role" : " Rol predeterminado ",
  " Employee" : " Empleado ",
  " employee " : " empleado   ",
  " has requested unavailability for this shift." : " ha solicitado la no disponibilidad para este turno. ",
  " has shift" : " tiene turno ",
  " Hour " : " Hora   ",
  " Leave" : " Excedencia ",
  " Managers" : " Directivos ",
  " Minute" : " Minuto ",
  " on " : "    ",
  " Payment successfully added." : " El pago ha añadido satisfactoriamente. ",
  " per hour" : " por hora ",
  " per shift" : " por turno ",
  " Publish Week " : " Semana de publicación   ",
  " Repeating every " : " Repetir cada   ",
  " shift" : " turno ",
  " Un-publish Week " : " Semana De Las Naciones Unidas   ",
  " will be invited to join, " : " se invitará a unirse,   ",
  "0 Hour" : "0 Hora ",
  "0 hours " : "0 horas   ",
  "0 Manager" : "0 Gerente ",
  "0 Minutes" : "0 Minutos ",
  "2 Week" : "2 Semana ",
  "3 Week" : "3 Semana ",
  "4 Week" : "4 Semana ",
  "<br>Email send Successfully." : "<br>Enviar correo electrónico correctamente. ",
  "A fresh verification link has been sent to your email address." : "Se ha enviado un nuevo enlace de verificación a su dirección de correo electrónico. ",
  "Absent Employee" : "Empleado ausente ",
  "Account settings" : "Valores de cuenta ",
  "Account Type" : "Tipo de cuenta ",
  "Action" : "Acción ",
  "Active" : "Activo ",
  "Add" : "Añadir ",
  "Add Annual Leave" : "Añadir permiso anual ",
  "Add day off successfully" : "Añadir el día de salida satisfactoriamente ",
  "Add Employee Leave" : "Añadir permiso de empleado ",
  "Add employees and manage basic information (email, locations, roles, allowances, etc)" : "Añadir empleados y gestionar información básica (correo electrónico, ubicaciones, roles, asignaciones, etc.) ",
  "Add New Availability" : "Añadir nueva disponibilidad ",
  "Add New Availability Pattern" : "Añadir nuevo patrón de disponibilidad ",
  "Add New Embargoes" : "Añadir nuevas embargos ",
  "Add New Employee" : "Añadir nuevo empleado ",
  "Add New Group" : "Añadir nuevo grupo ",
  "Add New Leave" : "Añadir nueva licencia ",
  "Add New Location" : "Añadir ubicación nueva ",
  "Add New Role" : "Añadir nuevo rol ",
  "Add New Rule" : "Añadir regla nueva ",
  "Add New Shift" : "Añadir nuevo turno ",
  "Add/Remove Employee" : "Añadir/Eliminar empleado ",
  "Added" : "Añadido ",
  "Additional Settings" : "Configuración adicional ",
  "Address" : "Dirección ",
  "Admin" : "Administrador ",
  "Administrator" : "Administrador ",
  "Already have an acocunt?" : "¿Ya tiene un acócunt? ",
  "Annual Holiday Allowance" : "Asignación anual de vacaciones ",
  "Anyone with the link" : "Cualquier persona con el enlace ",
  "Applies To" : "Se aplica a ",
  "Apply" : "Aplicar ",
  "Apply To" : "Aplicar a ",
  "Approve" : "Aprobar ",
  "APPROVED" : "APROBADO ",
  "approved this leave request" : "aprobada esta solicitud de licencia ",
  "April" : "Abril ",
  "Are You Sure?" : "¿estás Seguro? ",
  "August" : "Agosto ",
  "Auto Generate" : "Generar automáticamente ",
  "Availability" : "Disponibilidad ",
  "Availability Preferences" : "Preferencias de disponibilidad ",
  "Back to Rota Builder" : "Volver a Rota Builder ",
  "Back to?" : "¿De vuelta a? ",
  "Basic" : "Básica ",
  "Before proceeding, please check your email for a verification link." : "Antes de proceder, compruebe su correo electrónico para ver un enlace de verificación. ",
  "Break" : "Break ",
  "Buy Plan" : "Plan de compra ",
  "Calendar" : "Calendario ",
  "Can't work this shift ?" : "¿No puede funcionar este cambio? ",
  "Change Password" : "Cambiar contraseña ",
  "Choose a file" : "Elegir un archivo ",
  "Choose a file…" : "Elija un archivo ... ",
  "City" : "Ciudad ",
  "Clear Week" : "Semana clara ",
  "Click a day to set employees day off" : "Haga clic en un día para desactivar el día de los empleados ",
  "click here to request another" : "haga clic aquí para solicitar otro ",
  "Click to Upgrade Plan" : "Pulse para actualizar el plan ",
  "Client ID" : "ID de cliente ",
  "Code" : "Código ",
  "Colour" : "Color ",
  "Comapany Name" : "Nombre Comapany ",
  "Company" : "Empresa ",
  "Company Details" : "Detalles de empresa ",
  "Company leave : " : "Licencia de empresa:   ",
  "Company Logo" : "Logotipo de empresa ",
  "Company Name" : "Nombre de empresa ",
  "Company owner" : "Propietario de empresa ",
  "Company Telephone Number" : "Número telefónico de la empresa ",
  "Confirm Password" : "Confirmar contraseña ",
  "Connection timeout" : "Tiempo de espera ",
  "Contact Details" : "Datos de contacto ",
  "Copied the text: " : "Copiado el texto:   ",
  "Copy Shift" : "Copiar Mayús. ",
  "Cost" : "Coste ",
  "Country" : "País ",
  "Coupon" : "Cupón ",
  "Coupon code has applied successfully." : "El código de cupón se ha aplicado correctamente. ",
  "Coupon Detail" : "Detalle del cupón ",
  "Coupon successfully created." : "Cupón creado correctamente. ",
  "Coupon successfully deleted." : "Cupón suprimido correctamente. ",
  "Coupon successfully updated." : "Cupón actualizado correctamente. ",
  "Create" : "Crear ",
  "Create account" : "Crear cuenta ",
  "Create Link" : "Crear enlace ",
  "Create my account" : "Crear mi cuenta ",
  "Create New Coupon" : "Crear nuevo cupón ",
  "Create New Language" : "Crear nuevo idioma ",
  "Create,edit and delete rotas for locations they manage" : "Crear, editar y suprimir rotas para las ubicaciones que gestionan ",
  "Credit / Debit Card" : "Tarjeta de crédito/débito ",
  "Currency *" : "Moneda ",
  "Currency Symbol" : "Símbolo de moneda ",
  "Currency Symbol *" : "Símbolo de moneda * ",
  "Current month leave" : "Licencia por mes ",
  "Current month new employee" : "Nuevo empleado del mes actual ",
  "Current month rotas" : "Rotas del mes en curso ",
  "Current Password" : "Contraseña actual ",
  "Custom Role Rates" : "Tasas de rol personalizadas ",
  "Daily Totals" : "Totales diarios ",
  "Dark Mode" : "Modo oscuro ",
  "Dashboard" : "Dashboard ",
  "Dashbord" : "Dashbord ",
  "Dashbord Setting" : "Configuración de Dashbord ",
  "Date" : "Fecha ",
  "Date Format" : "Formato de fecha ",
  "Date of Birth" : "Fecha de nacimiento ",
  "Day" : "Día ",
  "Day Off" : "Día apagado ",
  "days" : "días ",
  "Days" : "Días ",
  "December" : "Diciembre ",
  "Default Allowance" : "Asignación predeterminada ",
  "Default Break" : "Interrupción predeterminada ",
  "Default Language" : "Idioma predeterminado ",
  "Default Wage / Salary" : "Salario por defecto/Salario ",
  "Delete" : "Suprimir ",
  "Delete Succsefully" : "Suprimir Sucsefully ",
  "Deleted" : "Suprimido ",
  "DELETED" : "SUPRIMIDO ",
  "Deleted Employees" : "Empleados suprimidos ",
  "DENIED" : "DENIED ",
  "Deny" : "Denegar ",
  "Description" : "Descripción ",
  "Details about your Company information" : "Detalles sobre la información de su empresa ",
  "Details about your Employee & Personal information" : "Detalles sobre el empleado y la información personal ",
  "Details about your Location information" : "Detalles sobre la información de ubicación ",
  "Details about your plan paypal payment" : "Detalles sobre el pago del plan de pago ",
  "Details about your plan stript payment" : "Detalles sobre el pago del plan de pago ",
  "Details about your Roles information" : "Detalles sobre la información de Roles ",
  "Details about your Wage & Salary" : "Detalles sobre su salario y salario ",
  "Details about your Work Schedule" : "Detalles sobre la planificación de trabajo ",
  "Details of your rotas for this week." : "Detalles de sus rotas para esta semana. ",
  "Discount" : "Descuento ",
  "Discount (%)" : "Descuento (%) ",
  "Don't have an account? Create your account, it takes less than a minute" : "¿No tiene una cuenta?  Crea tu cuenta, toma menos de un minuto ",
  "Drag and drop shift to other location" : "Arrastrar y soltar desplazamiento a otra ubicación ",
  "Duration" : "Duración ",
  "E-Mail Address" : "Dirección de correo electrónico ",
  "E-Mail has been not sent due to SMTP configuration" : "El correo electrónico no se ha enviado debido a la configuración de SMTP ",
  "Edit" : "Editar ",
  "Edit Coupon" : "Editar cupón ",
  "Edit Embargoe" : "Editar Embargo ",
  "Edit Group" : "Editar grupo ",
  "Edit Groups" : "Editar grupos ",
  "Edit Leave" : "Editar permiso ",
  "Edit Location" : "Editar ubicación ",
  "Edit Plan" : "Editar plan ",
  "Edit Request" : "Editar solicitud ",
  "Edit Rule" : "Editar regla ",
  "Edit Shift" : "Editar turno ",
  "Email" : "Correo electrónico ",
  "Email address" : "Dirección electrónica ",
  "Email Address" : "Dirección electrónica ",
  "Email Already Exist" : "El Correo Electrónico Ya Existe ",
  "Email already exists" : "El correo electrónico ya existe ",
  "Email send Successfully." : "Enviar correo electrónico correctamente. ",
  "Email Setting" : "Configuración del correo ",
  "Embargo" : "Embargo ",
  "Embargoe Add Successfully" : "Embargoe Añadir correctamente ",
  "Embargoe Update Successfully" : "Actualización De Embargoe Satisfactoriamente ",
  "Embargoes" : "Embargos ",
  "Emergency Contact" : "Contacto de emergencia ",
  "Emergency Contact Name" : "Nombre de contacto de emergencia ",
  "Emergency Contact Phone Number" : "Teléfono de contacto de emergencia ",
  "Employee" : "Empleado ",
  "Employee Add Successfully" : "El empleado se añade correctamente ",
  "Employee Detail" : "Detalle del empleado ",
  "Employee Remove this location" : "Empleado Eliminar esta ubicación ",
  "Employee Restored Succsefully" : "Empleado restaurado de forma sucesiva ",
  "Employee Role" : "Rol de empleado ",
  "Employee Totals" : "Total de empleados ",
  "Employees" : "Empleados ",
  "Employees can only see notes for their own shifts" : "Los empleados sólo pueden ver notas para sus propios turnos ",
  "Employees can only see notes for their own shifts and open shifts" : "Los empleados sólo pueden ver notas para sus propios turnos y turnos abiertos ",
  "Employees can see shift notes for everybody" : "Los empleados pueden ver notas de turno para todo el mundo ",
  "Employees can set their own availability preferences" : "Los empleados pueden establecer sus propias preferencias de disponibilidad ",
  "Employees can view the rotas of locations they are not assigned to" : "Los empleados pueden ver las rotaciones de las ubicaciones a las que no están asignados ",
  "Employees only see themselves on the rota" : "Los empleados sólo se ven a sí mismos en la rota ",
  "Employment Type" : "Tipo de empleo ",
  "Enable Paypal" : "Habilitar Paypal ",
  "Enable Stripe" : "Habilitar banda ",
  "End Date" : "Fecha final ",
  "End Time" : "Hora de finalización ",
  "End time always greater then start time." : "Hora de finalización siempre mayor que la hora de inicio. ",
  "Enter Coupon Code" : "Introducir código de cupón ",
  "Enter Email Address" : "Especificar dirección de correo electrónico ",
  "Enter Footer Link 1" : "Especifique el enlace de pie de página 1 ",
  "Enter Footer Link 2" : "Especifique el enlace de pie de página 2 ",
  "Enter Footer Link 3" : "Introduzca el enlace de pie de página 3 ",
  "Enter Footer Link Title 1" : "Escriba el título de enlace de pie de página ",
  "Enter Footer Link Title 2" : "Escriba el título de enlace de pie de página ",
  "Enter Footer Link Title 3" : "Escriba el título de enlace de pie de página ",
  "Enter Mail Driver" : "Escriba el controlador de correo ",
  "Enter Mail Encryption" : "Especifique el cifrado de correo ",
  "Enter Mail From Address" : "Cómo introducir correo desde la dirección ",
  "Enter Mail Password" : "Introduzca la contraseña de correo ",
  "Enter Mail Port" : "Especifique el puerto de correo ",
  "Enter Mail Username" : "Introduzca el nombre de usuario ",
  "Enter new Language Code" : "Introduzca un nuevo código de idioma ",
  "Enter Password" : "Introduzca la contraseña ",
  "Enter Plan Name" : "Especifique el nombre del plan ",
  "Enter Plan Price" : "Especifique el precio del plan ",
  "Enter Stripe Key" : "Especifique la clave de banda ",
  "Enter Stripe Secret" : "Especifique el secreto de banda ",
  "Enter User Email" : "Escriba el correo electrónico de ",
  "Enter User Name" : "Especifique el nombre de usuario ",
  "Enter User Password" : "Especifique la contraseña de usuario ",
  "Enter Your Email" : "Introduzca su correo electrónico ",
  "Enter your email below to proceed." : "Introduzca su correo electrónico a continuación para continuar. ",
  "Error" : "Error ",
  "Expired : " : "Caducado:   ",
  "Favicon" : "Favicon ",
  "February" : "Febrero ",
  "Filter Location" : "Ubicación del filtro ",
  "Filter Role" : "Rol de filtro ",
  "Final Working Date" : "Fecha final de trabajo ",
  "First Name" : "Nombre: ",
  "Footer Link href 1" : "Pie de enlace href 1 ",
  "Footer Link href 2" : "Enlace de pie de página 2 ",
  "Footer Link href 3" : "Enlace de pie de página 3 ",
  "Footer Link Title 1" : "Pie de enlace Título 1 ",
  "Footer Link Title 2" : "Enlace de pie de página Título ",
  "Footer Link Title 3" : "Pie de enlace Título 3 ",
  "Footer Text" : "Texto del pie ",
  "for" : "para ",
  "Forgot Your Password?" : "¿ha olvidado Su Contraseña? ",
  "Free" : "Libre ",
  "Fri" : "Fri ",
  "Friday" : "Viernes ",
  "Gender" : "Sexo ",
  "Group Add Successfully" : "El grupo se añade correctamente ",
  "Group Name" : "Nombre del grupo ",
  "Group Update Successfully" : "Actualización de grupo satisfactoriamente ",
  "Groups" : "Grupos ",
  "has" : "tiene ",
  "Hi  '.$user->first_name." : "Hi '. $user-> first_name. ",
  "Hide" : "Ocultar ",
  "Hii , " : "Hii,   ",
  "holiday" : "vacaciones ",
  "Holiday" : "Vacaciones ",
  "Holiday Allowance" : "Asignación por vacaciones ",
  "Holiday Leave" : "Vacaciones vacaciones ",
  "Holiday Remaining" : "Vacaciones pendientes ",
  "Holiday Used" : "Vacaciones utilizadas ",
  "Hour" : "Hora ",
  "hour" : "hora ",
  "Hour " : "Hora   ",
  "Hourly cost" : "Coste por hora ",
  "Hours" : "Horas ",
  "hours" : "horas ",
  "Hours & Costs" : "Horas y costes ",
  "Hours for" : "Horas para ",
  "hours per week" : "horas por semana ",
  "If you add availabiliti of same date than system will refer last record" : "Si añade disponibilidad de la misma fecha que el sistema, el último registro ",
  "If you did not receive the email" : "Si no ha recibido el correo electrónico ",
  "Image" : "Imagen ",
  "Information Update Successfully" : "Actualización de la información correctamente ",
  "Invalid amount." : "Importe no válido. ",
  "Invoice" : "Factura ",
  "is contracted" : "se contrae ",
  "January" : "Enero ",
  "July" : "Julio ",
  "June" : "Junio ",
  "Labels" : "Etiquetas ",
  "Landing Page Display" : "Visualización de página de destino ",
  "Language" : "Lengua ",
  "Language Changed Successfully!" : "El idioma ha cambiado satisfactoriamente. ",
  "Language Code" : "Código de idioma ",
  "Language Created Successfully!" : "El lenguaje se ha creado correctamente ",
  "Language Deleted Successfully!" : "Idioma Suprimido Correctamente. ",
  "Language Saved Successfully!" : "El idioma se ha guardado correctamente ",
  "Last Name" : "Apellido ",
  "Leave" : "Excedencia ",
  "Leave Add Successfully" : "Dejar Añadir satisfactoriamente ",
  "Leave by Employee" : "Licencia por empleado ",
  "Leave Can Not Be Requested Over '.$embargos_date.'" : "No Se Puede Solicitar La Licencia En '. $embargos_date.' ",
  "Leave Embargoes" : "Dejar Embargos ",
  "Leave Request" : "Solicitud de licencia ",
  "Leave Request '.$status.' Successfully" : "Leave Request '. $status.'  Con éxito ",
  "Leave Request Add Successfully" : "La solicitud de permiso se añade ",
  "Leave Request Cancel Succsefully" : "Cancelar solicitud Cancelar Sucsefully ",
  "Leave Request Reply" : "Solicitar respuesta de solicitud ",
  "Leave Requests" : "Solicitudes de licencia ",
  "Leave requests available" : "Dejar las solicitudes disponibles ",
  "Leave Totals" : "Dejar totales ",
  "Leave Year Starts" : "Inicio de año de licencia ",
  "Light Mode" : "Modo luminoso ",
  "Limit" : "Límite ",
  "Link copied successfully." : "Enlace copiado satisfactoriamente. ",
  "Link created successfully." : "Enlace creado satisfactoriamente. ",
  "Live" : "Viva ",
  "Location" : "Ubicación ",
  "Location Add Successfully" : "La ubicación se añade correctamente ",
  "Location Setting" : "Configuración de ubicación ",
  "Location Totals" : "Totales de ubicación ",
  "Location Update Successfully" : "Actualización de ubicación correctamente ",
  "Locations" : "Ubicaciones ",
  "Locations Managed" : "Ubicaciones gestionadas ",
  "Login" : "Iniciar sesión ",
  "Logo" : "Logotipo ",
  "Logout" : "Cierre ",
  "Mail Driver" : "Controlador de correo ",
  "Mail Encryption" : "Cifrado de correo ",
  "Mail From Address" : "Correo De La Dirección ",
  "Mail From Name" : "Correo De Nombre ",
  "Mail Host" : "Host de correo ",
  "Mail Password" : "Contraseña de correo ",
  "Mail Port" : "Puerto de correo ",
  "Mail Send Successfully" : "Enviar correo con éxito ",
  "Mail Username" : "Nombre de usuario ",
  "Manage leave and approve leave requests for others and approve leave requests for others" : "Gestionar permisos de salida y aprobación de permisos para otros y aprobar solicitudes de permisos para otros ",
  "Manage leave embargoes" : "Gestionar los embargos de licencia ",
  "Manage roles" : "Gestionar roles ",
  "Manage type" : "Gestionar tipo ",
  "Manage user type" : "Gestionar el tipo de usuario ",
  "Manager" : "Gestor ",
  "Managers" : "Directivos ",
  "Manual" : "Manual ",
  "Manually" : "Manual ",
  "Manually add leave to themselves" : "Añadir permisos manualmente a sí mismos ",
  "Manually plan upgraded by super admin" : "Plan manual actualizado por super admin ",
  "March" : "Marzo ",
  "Maximum Employee" : "Empleado máximo ",
  "May" : "Mayo ",
  "Menu" : "Menú ",
  "Message" : "Mensaje ",
  "Messages" : "Mensajes ",
  "Middle Name" : "Nombre Medio ",
  "Minute" : "Minuto ",
  "minute" : "minuto ",
  "Minutes" : "Minutos ",
  "Mon" : "LON ",
  "Monday" : "Lunes ",
  "Monthly Totals" : "Totales mensuales ",
  "Most Purchase Plan" : "Plan de compra más ",
  "My profile" : "Mi perfil ",
  "Name" : "Nombre ",
  "Name on card" : "Nombre en tarjeta ",
  "New Password" : "Nueva contraseña ",
  "No availability found...!" : "No se ha encontrado disponibilidad ... ",
  "No Data Found" : "No se han encontrado datos ",
  "No data found...!" : "No se han encontrado datos ... ",
  "No embargoes found...!" : "¡No se encuentran embargos ...! ",
  "No Employee found...!" : "No se ha encontrado ningún empleado ... ",
  "No leave request found...!" : "No se ha encontrado ninguna solicitud de licencia ... ",
  "No loaction found...!" : "No se ha encontrado ninguna loacción ...! ",
  "No Manager" : "Sin gestor ",
  "No Role found...!" : "No se ha encontrado ningún rol ... ",
  "No shift available." : "No hay cambio disponible. ",
  "No user found." : "No se ha encontrado usuario. ",
  "not assign this location." : "no asignar esta ubicación. ",
  "Not registered" : "No registrado ",
  "Not registered?" : "¿No está registrado? ",
  "Note" : "Nota: ",
  "Note: \"-1\" for Unlimited" : "Nota: \"-1\" para Unlimited ",
  "Note: Add currency code as per three-letter ISO code." : "Nota: Añadir código de moneda según el código ISO de tres letras. ",
  "Note: Discount in Percentage" : "Nota: Descuento en porcentaje ",
  "Notes" : "Notas ",
  "November" : "Noviembre ",
  "October" : "Octubre ",
  "Only admins and managers can see shift notes" : "Sólo los administradores y administradores pueden ver notas de turno ",
  "Only people with the password" : "Sólo personas con la contraseña ",
  "Opps..." : "Opps ... ",
  "Order" : "Orden ",
  "Order Id" : "ID de pedido ",
  "Order Summary" : "Resumen de pedidos ",
  "Other Leave" : "Otros permisos ",
  "other leave" : "Otros permisos ",
  "other Leave" : "Otros permisos ",
  "Other leave : " : "Otros permisos:   ",
  "Paid" : "Pagada ",
  "Paid Users" : "Usuarios pagados ",
  "Paid/Unpaid Leave" : "Vacaciones pagadas/sin pagar ",
  "Password" : "Contraseña ",
  "Password reset" : "Restablecimiento de contraseña ",
  "Password Set Succsefully" : "Conjunto de contraseñas Sucsefully ",
  "Password successfully updated." : "Contraseña actualizada correctamente. ",
  "Past Employees" : "Empleados anteriores ",
  "Pay Now" : "Pagar ahora ",
  "Payment failed" : "Error de pago ",
  "Payment setting successfully saved." : "Valor de pago guardado correctamente. ",
  "Payment Settings" : "Valores de pago ",
  "Payment successfully added" : "El pago ha añadido satisfactoriamente ",
  "Payment Type" : "Tipo de pago ",
  "PAYPAL" : "PAYPAL ",
  "PayPal" : "PayPal ",
  "Paypal" : "Paypal ",
  "Paypal Mode" : "Modo Paypal ",
  "Per Hour" : "Por hora ",
  "Per Shift" : "Por turno ",
  "Permission" : "Permiso ",
  "Permission denied" : "Permiso denegado ",
  "Permission denied." : "Permiso denegado. ",
  "Permissions" : "Permisos ",
  "Personal Detail" : "Detalle personal ",
  "Phone Number" : "Número de teléfono ",
  "Plan" : "Plan ",
  "Plan activated Successfully." : "Plan activado con éxito. ",
  "Plan Expired" : "Plan Caducado ",
  "Plan is deleted." : "El plan se suprime. ",
  "Plan Name" : "Nombre del plan ",
  "Plan not found." : "Plan no encontrado. ",
  "Plan successfully activated." : "Plan correctamente activado. ",
  "Plan Successfully created." : "Plan creado correctamente. ",
  "Plan successfully updated." : "Plan actualizado correctamente. ",
  "Please assign user in this location." : "Asigne al usuario en esta ubicación. ",
  "Please confirm your password before continuing." : "Confirme su contraseña antes de continuar. ",
  "Please correct the errors and try again." : "Corrija los errores y vuelva a intentarlo. ",
  "Please enter correct current password." : "Especifique la contraseña actual correcta. ",
  "Please select roll" : "Por favor, seleccione rollo ",
  "Please select User" : "Seleccione Usuario ",
  "Please set stripe api key & secret key for add new plan." : "Establezca la clave de la API de banda y la clave secreta para añadir un plan nuevo. ",
  "Please set stripe or paypal api key & secret key for add new plan." : "Establezca la clave y la clave secreta de la api de banda o paypal para añadir un nuevo plan. ",
  "Please set stripe/paypal api key & secret key for add new plan" : "Establezca la clave de la API de banda/paypal y la clave secreta para añadir un nuevo plan ",
  "Please Try Again" : "Vuelva a intentarlo ",
  "Please Try Again." : "Vuelva A Intentarlo. ",
  "Post" : "Post ",
  "Postcode" : "Código postal ",
  "Pre" : "Pre ",
  "Present Employee" : "Empleado actual ",
  "Price" : "Precio ",
  "Print" : "Imprimir ",
  "Print rotas" : "Rotas de impresión ",
  "Profile" : "Perfil ",
  "Profile Image" : "Imagen del perfil ",
  "Public Holiday" : "Vacaciones públicas ",
  "Publish Rotas" : "Publicar Rotas ",
  "Re-send Invite" : "Volver a enviar Invite ",
  "Re-type New Password" : "Volver a escribir nueva contraseña ",
  "Recent Order" : "Orden reciente ",
  "Record Hours" : "Horas de registro ",
  "Regarding to User Login Invitation" : "Respecto a la invitación de inicio de sesión de ",
  "Register" : "Registro ",
  "Registration" : "Registro ",
  "Relationship to Employee" : "Relación con el empleado ",
  "Remove day off successfully" : "Eliminar el día con éxito ",
  "Repeat Every" : "Repetir cada ",
  "Reply" : "Respuesta ",
  "Report" : "Informe ",
  "Reports" : "Informes ",
  "Request Rules" : "Reglas de solicitud ",
  "Requested" : "Solicitado ",
  "requested" : "solicitado ",
  "REQUESTED" : "SOLICITADO ",
  "Reset password" : "Restablecer contraseña ",
  "Reset Password" : "Restablecer contraseña ",
  "Restore" : "Restaurar ",
  "Role" : "Función ",
  "Role Add Successfully" : "El rol se añade correctamente ",
  "Role Setting" : "Valor de rol ",
  "Role Totals" : "Totales de rol ",
  "Role Update Successfully" : "Actualización de roles satisfactoriamente ",
  "Roles" : "Funciones ",
  "Roles are different for both the user." : "Los roles son diferentes para el usuario. ",
  "Rota Settings" : "Configuración Rota ",
  "RotaGo Saas" : "RotaGo Saas ",
  "Rotas" : "Rotas ",
  "Rule" : "Artículo ",
  "Rule Add Successfully" : "La regla se añade correctamente ",
  "Rule Delete Succsefully" : "Suprimir la regla Sucsefully ",
  "Rule Update Successfully" : "Actualización de reglas correctamente ",
  "Rules" : "Normas ",
  "Safe money transfer using your bank account. We support Mastercard, Visa, Discover and American express." : "Transferencia segura de dinero usando su cuenta bancaria.  Apoyamos a Mastercard, Visa, Discover y American express. ",
  "Salary Setting" : "Valor salarial ",
  "Sandbox" : "Sandbox ",
  "Sat" : "Sat ",
  "Saturday" : "Sábado ",
  "Save" : "Guardar ",
  "Save Change" : "Guardar cambio ",
  "Save Changes" : "Guardar cambios ",
  "Search User" : "Usuario de búsqueda ",
  "Secret Key" : "Clave secreta ",
  "Select all" : "Seleccionar todos ",
  "Select All" : "Seleccionar todo ",
  "Select Day" : "Seleccionar el día ",
  "Select location" : "Seleccionar ubicación ",
  "Select Month" : "Seleccione Mes ",
  "Select Role" : "Seleccionar rol ",
  "Select role" : "Seleccionar rol ",
  "Select user" : "Seleccionar usuario ",
  "Select User" : "Seleccionar usuario ",
  "Send" : "Enviar ",
  "Send rotas via email" : "Enviar a las rotas por correo electrónico ",
  "Send Test Mail" : "Enviar correo de prueba ",
  "September" : "Septiembre ",
  "SET" : "SET ",
  "Set Location" : "Establecer ubicación ",
  "Set Password" : "Establecer contraseña ",
  "Set Role" : "Establecer rol ",
  "Setting" : "Ajuste ",
  "Setting successfully updated." : "Se ha actualizado correctamente. ",
  "Setting Update Successfully" : "Configurar la actualización correctamente ",
  "Settings" : "Configuración ",
  "Share links provide read-only access to your rotas. By default anyone with the link can view all past and future rotas for this location." : "Los enlaces compartidos proporcionan acceso de sólo lectura a las rotas.  De forma predeterminada, cualquier persona con el enlace puede ver todas las rotas pasadas y futuras para esta ubicación. ",
  "Share rotas" : "Compartir rotas ",
  "Shift Add Successfully" : "Mayús. Añadir satisfactoriamente ",
  "Shift Cancel" : "Cancelar el turno ",
  "Shift cost" : "Coste de desplazamiento ",
  "Shift Notes" : "Cambiar las notas ",
  "Shift Publish Successfully" : "Mayús. Publicar correctamente ",
  "Shift request " : "Solicitud de cambio   ",
  "Shift Un-Publish Successfully" : "Cambiar la publicación de Un-Publicar satisfactoriamente ",
  "Shift unavailability request sent." : "Solicitud de desdisponibilidad de turno enviada. ",
  "Shift Unavailability Requested" : "No Disponibilidad De Turno Solicitada ",
  "Shift unavailable request" : "Cambiar solicitud no disponible ",
  "Shift unavailable request approved" : "Solicitud de desplazamiento no disponible aprobada ",
  "Shift Update Successfully" : "Actualización de turno correctamente ",
  "Show" : "Mostrar ",
  "Show employee avatars on rota" : "Mostrar avatares de empleado en rota ",
  "Show employee rotas price" : "Mostrar rotas de empleados ",
  "Sign in" : "Signo en ",
  "Sign in to your account to continue." : "Inicie sesión en su cuenta para continuar. ",
  "Site Setting" : "Configuración del sitio ",
  "Some error occur, sorry for inconvenient" : "Se produce algún error, lo siento por inconveniente ",
  "Something is wrong." : "Algo está mal. ",
  "Something went wrong." : "Algo salió mal. ",
  "Something went wrong. please try again later." : "Algo salió mal.  Vuelva a intentarlo más tarde. ",
  "Start Date" : "Fecha de inicio ",
  "Start Time" : "Hora de inicio ",
  "Status" : "Estado ",
  "Stripe" : "Raya ",
  "STRIPE" : "BANDA ",
  "Stripe Key" : "Tecla de banda ",
  "Stripe Secret" : "Secreto de banda ",
  "Submit" : "Presentar ",
  "success" : "éxito ",
  "Sun" : "Sol ",
  "Sunday" : "Domingo ",
  "This action can not be undone. Do you want to continue?" : "Esta acción no se puede deshacer.  ¿Desea continuar? ",
  "This coupon code has expired." : "Este código de cupón ha caducado. ",
  "This coupon code is invalid or has expired." : "Este código de cupón no es válido o ha caducado. ",
  "This day already day off" : "Este día ya el día libre ",
  "This detail will use for make purchase of plan." : "Este detalle se utilizará para hacer la compra del plan. ",
  "This is" : "Esto es ",
  "This is " : "Esto es   ",
  "This Shift clashes " : "Este cambio de turno   ",
  "Thu" : "Jue ",
  "Thursday" : "Jueves ",
  "Time" : "Tiempo ",
  "Time Format" : "Formato de hora ",
  "Time Off & Cover" : "Tiempo apagado y cubierta ",
  "Title" : "Título ",
  "Title Text" : "Título Texto ",
  "Toggle navigation" : "Conmutar navegación ",
  "Total cost : " : "Coste total:   ",
  "Total Employee" : "Empleado total ",
  "Total employee : " : "Empleado total:   ",
  "Total Hours" : "Total Horas ",
  "Total Order Amount" : "Importe total del pedido ",
  "Total Orders" : "Total pedidos ",
  "Total Plans" : "Planes totales ",
  "Total time : " : "Tiempo total:   ",
  "Total Users" : "Total Usuarios ",
  "Transaction has been failed." : "La transacción ha fallado. ",
  "Tue" : "Tue ",
  "Tuesday" : "Martes ",
  "Type" : "Tipo ",
  "Unavailability Reason" : "Razón de no disponibilidad ",
  "Unavailability Requested" : "No disponibilidad solicitada ",
  "Unknown error occurred" : "Se produjo un error desconocido ",
  "Unlimited" : "Ilimitado ",
  "Unpaid" : "No remunerado ",
  "Unpaid/Paid" : "No remunerado/Pagado ",
  "Update" : "Actualización ",
  "Upgrade Plan" : "Plan de actualización ",
  "Use the work schedule to set your employee's regular days off. They will then display on the rota accordingly. Changes to work schedules will apply from the current day forwards." : "Utilice la planificación de trabajo para desactivar los días regulares de su empleado.  A continuación, se mostrarán en la rota en consecuencia.  Los cambios en las planificaciones de trabajo se aplicarán a partir del día actual. ",
  "Used" : "Utilizado ",
  "Used 100 % discount coupon code." : "Se utiliza código de cupón de descuento del 100%. ",
  "User" : "Usuario ",
  "User not found." : "Usuario no encontrado. ",
  "User successfully created." : "El usuario ha creado correctamente. ",
  "User successfully deleted." : "El usuario ha suprimido correctamente. ",
  "User successfully updated." : "El usuario ha actualizado correctamente. ",
  "Username" : "Nombre ",
  "Verify Your Email Address" : "Verifique Su Dirección De Correo Electrónico ",
  "View" : "Vista ",
  "View All Leave" : "Ver todas las licencias ",
  "View and edit employee salary information" : "Ver y editar información sobre salarios de empleados ",
  "View Employees" : "Ver empleados ",
  "View reports" : "Ver informes ",
  "Wage & Salary" : "Salario y salario ",
  "Wage / Salary" : "Salario/Salario ",
  "Wednesday" : "Miércoles ",
  "week" : "Semana ",
  "Week" : "Semana ",
  "Week Starts" : "Inicio de semana ",
  "Weekly Hours" : "Horas semanales ",
  "Welcome to " : "Bienvenido a   ",
  "Wen" : "Wen ",
  "Without role" : "Sin función ",
  "Without Role" : "Sin rol ",
  "Work Schedule" : "Planificación de trabajo ",
  "Working" : "Trabajar ",
  "You" : "Usted ",
  "you can find out here.." : "usted puede averiguar aquí .. ",
  "You must add a location to your account and assign user <br> before you can start building rotas." : "Debe añadir una ubicación a la cuenta y asignar el usuario <br> antes de empezar a crear rotas. ",
  "Your Account Details" : "Detalles de su cuenta ",
  "Your availability pattern has been added" : "Se ha añadido el patrón de disponibilidad ",
  "Your employee limit is over, Please upgrade plan." : "Su límite de empleados ha terminado, por favor, actualice el plan. ",
  "Your payment has failed." : "Su pago ha fallado."
}